PT92002UNO/__init__.py
PT92002UNO/metodos_lineales.py
PT92002UNO/metodos_no_lineales.py
PT92002UNO/utils.py
PT92002UNO-1.0.0.dist-info/LICENSE
PT92002UNO-1.0.0.dist-info/METADATA
PT92002UNO-1.0.0.dist-info/WHEEL
PT92002UNO-1.0.0.dist-info/top_level.txt
PT92002UNO-1.0.0.dist-info/RECORD
