Metadata-Version: 2.1
Name: PT92002UNO
Version: 1.0.0
Summary: Librería de métodos numéricos para resolver sistemas de ecuaciones lineales y no lineales
Home-page: https://github.com/tuusuario/PT92002UNO
Author: [Frany Esmeralda Peña Tobar]
Author-email: tobarfrany@gmail.com
Classifier: Programming Language :: Python :: 3
Classifier: License :: OSI Approved :: MIT License
Classifier: Operating System :: OS Independent
Classifier: Development Status :: 4 - Beta
Classifier: Intended Audience :: Education
Classifier: Intended Audience :: Science/Research
Classifier: Topic :: Scientific/Engineering :: Mathematics
Requires-Python: >=3.6
License-File: LICENSE
Requires-Dist: numpy>=1.19.0
